<level width="699.95" height="796.1">
  <levelObject spriteName="generalRoom_floorTile" xPos="319.15" yPos="7.35" xScale="1" yScale="1" rotation="0"/>
  <levelObject spriteName="generalRoom_floorTile" xPos="440.15" yPos="6.35" xScale="1" yScale="1" rotation="0"/>
  <levelObject spriteName="generalRoom_floorTile" xPos="133.8" yPos="127.7" xScale="1" yScale="1" rotation="0"/>
  <levelObject spriteName="generalRoom_floorTile" xPos="375.8" yPos="127.7" xScale="1" yScale="1" rotation="0"/>
  <levelObject spriteName="generalRoom_floorTile" xPos="254.8" yPos="127.7" xScale="1" yScale="1" rotation="0"/>
  <levelObject spriteName="generalRoom_floorTile" xPos="197.15" yPos="245.35" xScale="1" yScale="1" rotation="0"/>
  <levelObject spriteName="generalRoom_floorTile" xPos="318.15" yPos="245.35" xScale="1" yScale="1" rotation="0"/>
  <levelObject spriteName="generalRoom_floorTile" xPos="439.15" yPos="244.35" xScale="1" yScale="1" rotation="0"/>
  <levelObject spriteName="generalRoom_floorTile" xPos="165.15" yPos="366.3" xScale="1" yScale="1" rotation="0"/>
  <levelObject spriteName="generalRoom_floorTile" xPos="286.15" yPos="366.3" xScale="1" yScale="1" rotation="0"/>
  <levelObject spriteName="generalRoom_floorTile" xPos="407.15" yPos="365.3" xScale="1" yScale="1" rotation="0"/>
  <levelObject spriteName="generalRoom_floorTile" xPos="195.15" yPos="487.3" xScale="1" yScale="1" rotation="0"/>
  <levelObject spriteName="generalRoom_floorTile" xPos="316.15" yPos="486.3" xScale="1" yScale="1" rotation="0"/>
  <levelObject spriteName="generalRoom_floorTile" xPos="437.15" yPos="486.3" xScale="1" yScale="1" rotation="0"/>
  <levelObject spriteName="generalRoom_floorTile" xPos="182.15" yPos="606.3" xScale="1" yScale="1" rotation="0"/>
  <levelObject spriteName="generalRoom_floorTile" xPos="303.15" yPos="606.3" xScale="1" yScale="1" rotation="0"/>
  <levelObject spriteName="generalRoom_floorTile" xPos="424.15" yPos="606.3" xScale="1" yScale="1" rotation="0"/>
  <levelObject spriteName="generalRoom_topWall" xPos="251.2" yPos="2.45" xScale="1" yScale="1" rotation="0"/>
  <levelObject spriteName="generalRoom_upperRightCorner" xPos="452.7" yPos="2.1" xScale="1" yScale="1" rotation="0"/>
  <levelObject spriteName="generalRoom_sideWall" xPos="496.2" yPos="230.6" xScale="1" yScale="1" rotation="0"/>
  <levelObject spriteName="generalRoom_sideWall" xPos="496.2" yPos="430" xScale="1" yScale="1.00299072265625" rotation="0"/>
  <levelObject spriteName="generalRoom_lowerRightCorner" xPos="451.35" yPos="630.2" xScale="1" yScale="1" rotation="0"/>
  <levelObject spriteName="generalRoom_bottomWall" xPos="250.7" yPos="727.05" xScale="1" yScale="1" rotation="0"/>
  <levelObject spriteName="generalRoom_lowerLeftCorner" xPos="119.9" yPos="630.2" xScale="1" yScale="1" rotation="0"/>
  <levelObject spriteName="generalRoom_upperLeftCorner" xPos="119.95" yPos="2.2" xScale="1" yScale="1" rotation="0"/>
  <levelObject spriteName="generalRoom_sideWall" xPos="206.7" yPos="430.45" xScale="-1" yScale="1" rotation="0"/>
  <levelObject spriteName="generalRoom_sideWall" xPos="206.7" yPos="232.2" xScale="-1" yScale="1" rotation="0"/>
  <levelObject spriteName="generalRoom_floorTile" xPos="296.3" yPos="676.05" xScale="0.811492919921875" yScale="0.5869903564453125" rotation="0"/>
  <levelObject spriteName="generalRoom_bottomDoor" xPos="276.15" yPos="721.05" xScale="1" yScale="1" rotation="0"/>
  <levelObject spriteName="generalRoom_floorTile" xPos="297.15" yPos="90.45" xScale="0.841064453125" yScale="0.8299407958984375" rotation="0"/>
  <levelObject spriteName="generalRoom_topDoor" xPos="280.15" yPos="53.35" xScale="1" yScale="1" rotation="0"/>
  <levelObject spriteName="generalRoom_purple_floorRunnerTop" xPos="250.45" yPos="214.5" xScale="1" yScale="1" rotation="0"/>
  <levelObject spriteName="generalRoom_purple_floorRunnerMid2" xPos="250.45" yPos="307.35" xScale="1" yScale="1" rotation="0"/>
  <levelObject spriteName="generalRoom_purple_floorRunnerMid1" xPos="250.45" yPos="427.85" xScale="1" yScale="1" rotation="0"/>
  <levelObject spriteName="generalRoom_purple_floorRunnerTop" xPos="451.45" yPos="714.45" xScale="1" yScale="1" rotation="180"/>
  <levelObject spriteName="generalRoom_purple_floorRunner_rotationConnect" xPos="250.55" yPos="617.55" xScale="1" yScale="1" rotation="0"/>
  <levelObject spriteName="generalRoom_purple_floorRunnerMid1" xPos="250.55" yPos="549.6" xScale="1" yScale="0.556976318359375" rotation="0"/>
  <levelObject spriteName="generalRoom_sideTorch_undead" xPos="496.3" yPos="606.35" xScale="1" yScale="1" rotation="0"/>
  <levelObject spriteName="generalRoom_sideTorch_undead" xPos="496.3" yPos="394.3" xScale="1" yScale="1" rotation="0"/>
  <levelObject spriteName="generalRoom_sideTorch_undead" xPos="213.4" yPos="506.4" xScale="-1" yScale="1" rotation="0"/>
  <levelObject spriteName="generalRoom_sideTorch_undead" xPos="213.4" yPos="294.3" xScale="-1" yScale="1" rotation="0"/>
  <levelObject spriteName="generalRoom_genericTapestrySide_undead" xPos="209.5" yPos="371.4" xScale="-1" yScale="1" rotation="0"/>
  <levelObject spriteName="generalRoom_genericTapestrySide_undead" xPos="493.45" yPos="471.4" xScale="1" yScale="1" rotation="0"/>
  <levelObject spriteName="generalRoom_sideTable_bottom" xPos="447.8" yPos="476" xScale="1" yScale="1" rotation="0"/>
  <levelObject spriteName="generalRoom_sideTable_center" xPos="449.8" yPos="441.85" xScale="1" yScale="1" rotation="0"/>
  <levelObject spriteName="generalRoom_sideTable_top" xPos="447.15" yPos="355.8" xScale="1" yScale="1" rotation="0"/>
  <levelObject spriteName="generalRoom_sideTable_center" xPos="449.3" yPos="407.85" xScale="1" yScale="1" rotation="0"/>
  <levelObject spriteName="generalRoom_tableRunner" xPos="489.5" yPos="362" xScale="1.2255706787109375" yScale="1" rotation="90"/>
  <levelObject spriteName="generalRoom_tableSkeleton" xPos="501.5" yPos="410" xScale="1" yScale="1" rotation="90"/>
  <levelObject spriteName="generalRoom_genericTapestrySide_undead" xPos="492.45" yPos="271.4" xScale="1" yScale="1" rotation="0"/>
  <levelObject spriteName="generalRoom_sideTorch_undead" xPos="496.3" yPos="194.3" xScale="1" yScale="1" rotation="0"/>
  <levelObject spriteName="generalRoom_sideTorch_undead" xPos="213.4" yPos="204.3" xScale="-1" yScale="1" rotation="0"/>
  <levelObject spriteName="generalRoom_sideTorch_undead" xPos="213.4" yPos="596.4" xScale="-1" yScale="1" rotation="0"/>
  <levelObject spriteName="generalRoom_goldFloorVase" xPos="418.5" yPos="103" xScale="1" yScale="1" rotation="0"/>
  <levelObject spriteName="generalRoom_goldFloorVase" xPos="201.5" yPos="103" xScale="1" yScale="1" rotation="0"/>
  <levelObject spriteName="collRect" xPos="600.3" yPos="347.35" xScale="1" yScale="1" rotation="0"/>
  <levelObject spriteName="collRect" xPos="0.35" yPos="341.35" xScale="1" yScale="1" rotation="0"/>
  <levelObject spriteName="collRect" xPos="496.3" yPos="182.2" xScale="0.3285064697265625" yScale="11.039443969726563" rotation="0"/>
  <levelObject spriteName="collRect" xPos="172.35" yPos="185.2" xScale="0.3285064697265625" yScale="11.039443969726563" rotation="0"/>
  <levelObject spriteName="collRect" xPos="399.15" yPos="140.45" xScale="1.149932861328125" yScale="1" rotation="0"/>
  <levelObject spriteName="collRect" xPos="185.15" yPos="135.2" xScale="1.149932861328125" yScale="1" rotation="0"/>
  <levelObject spriteName="collRect" xPos="396.85" yPos="726.2" xScale="1.149932861328125" yScale="1" rotation="0"/>
  <levelObject spriteName="collRect" xPos="182.85" yPos="728.95" xScale="1.149932861328125" yScale="1" rotation="0"/>
  <levelObject spriteName="collRect" xPos="436.8" yPos="165.45" xScale="0.48333740234375" yScale="1" rotation="0"/>
  <levelObject spriteName="collRect" xPos="220.5" yPos="171.2" xScale="0.48333740234375" yScale="1" rotation="0"/>
  <levelObject spriteName="entryObject5" xPos="330.3" yPos="175.35" xScale="1" yScale="1" rotation="0"/>
  <levelObject spriteName="roomTransitionObject5" xPos="300.1" yPos="117.85" xScale="1.48699951171875" yScale="0.6712799072265625" rotation="0"/>
  <levelObject spriteName="roomTransitionObject4" xPos="297.9" yPos="730.8" xScale="1.6107635498046875" yScale="0.473876953125" rotation="0"/>
  <levelObject spriteName="entryObject4" xPos="325.3" yPos="677.3" xScale="1" yScale="1" rotation="0"/>
  <levelObject spriteName="collRect" xPos="462.85" yPos="359" xScale="0.48333740234375" yScale="3.41998291015625" rotation="0"/>
</level>